pytadacs/__init__.py
pytadacs-0.0.1.dist-info/LICENSE
pytadacs-0.0.1.dist-info/METADATA
pytadacs-0.0.1.dist-info/WHEEL
pytadacs-0.0.1.dist-info/top_level.txt
pytadacs-0.0.1.dist-info/RECORD
