Metadata-Version: 2.1
Name: pytadacs
Version: 0.0.1
Summary: pytadacs: Python for Tess Astroseismic and DynAmiC Studies
Author: Rafael A. García
Author-email: rafel.garcia@ecea.fr
Classifier: Programming Language :: Python :: 3
Classifier: License :: OSI Approved :: GNU Lesser General Public License v3 (LGPLv3)
Classifier: Operating System :: OS Independent
Requires-Python: >=3.6
License-File: LICENSE
Requires-Dist: numpy
